pypartpicker/__init__.py
pypartpicker/client.py
pypartpicker/errors.py
pypartpicker/regex.py
pypartpicker/scraper.py
pypartpicker/types.py
pypartpicker/urls.py
pypartpicker-2.0.5.dist-info/METADATA
pypartpicker-2.0.5.dist-info/WHEEL
pypartpicker-2.0.5.dist-info/RECORD
