Metadata-Version: 2.1
Name: pypartpicker
Version: 2.0.5
Summary: A PCPartPicker data extractor for Python.
Home-page: https://github.com/thefakequake/pypartpicker
Keywords: pcpartpicker,pcpp,scraping
Author: QuaKe
Requires-Python: >=3.10,<4.0
Classifier: Programming Language :: Python :: 3
Classifier: Programming Language :: Python :: 3.10
Classifier: Programming Language :: Python :: 3.11
Classifier: Programming Language :: Python :: 3.12
Classifier: Programming Language :: Python :: 3.13
Requires-Dist: lxml[html-clean] (>=5.3.0,<6.0.0)
Requires-Dist: requests-html (>=0.10.0,<0.11.0)
Project-URL: Repository, https://github.com/thefakequake/pypartpicker
